MANIFEST.in
README.md
requirements.txt
setup.py
scripts/toolbox_joacripp-run
tests/__init__.py
tests/test_preprocessing.py
toolbox_joacripp/__init__.py
toolbox_joacripp/preprocessing.py
toolbox_joacripp.egg-info/PKG-INFO
toolbox_joacripp.egg-info/SOURCES.txt
toolbox_joacripp.egg-info/dependency_links.txt
toolbox_joacripp.egg-info/not-zip-safe
toolbox_joacripp.egg-info/requires.txt
toolbox_joacripp.egg-info/top_level.txt